[{"pk": "01", "model": "quiz.Collaborateur", "fields": {}},
{"pk": "02", "model": "quiz.Collaborateur", "fields": {}},
{"pk": "03", "model": "quiz.Collaborateur", "fields": {}},
{"pk": "04", "model": "quiz.Collaborateur", "fields": {}},
{"pk": "05", "model": "quiz.Collaborateur", "fields": {}},
{"pk": "06", "model": "quiz.Collaborateur", "fields": {}},
{"pk": "07", "model": "quiz.Collaborateur", "fields": {}},
{"pk": "08", "model": "quiz.Collaborateur", "fields": {}},
{"pk": "09", "model": "quiz.Collaborateur", "fields": {}}
]